spikify/__init__.py
spikify/manager/__init__.py
spikify/manager/thread_manager.py
spikify/util/__init__.py
spikify/util/singleton_util.py
spikify-0.0.1.dist-info/METADATA
spikify-0.0.1.dist-info/WHEEL
spikify-0.0.1.dist-info/RECORD
