Metadata-Version: 2.1
Name: spikify
Version: 0.0.1
Summary: 迅速提升开发效率的工具包
Author: seehar
Author-email: seehar@qq.com
Requires-Python: >=3.8,<4.0
Classifier: Programming Language :: Python :: 3
Classifier: Programming Language :: Python :: 3.8
Classifier: Programming Language :: Python :: 3.9
Classifier: Programming Language :: Python :: 3.10
Classifier: Programming Language :: Python :: 3.11
Classifier: Programming Language :: Python :: 3.12
